efficienpy/__init__.py
efficienpy/cli.py
efficienpy/efficienpy.py
efficienpy-0.1.1.dist-info/AUTHORS.rst
efficienpy-0.1.1.dist-info/LICENSE
efficienpy-0.1.1.dist-info/METADATA
efficienpy-0.1.1.dist-info/WHEEL
efficienpy-0.1.1.dist-info/RECORD
