Metadata-Version: 2.1
Name: efficienpy
Version: 0.1.1
Summary: A comprehensive Python package designed to simplify daily workflows, enhance data processing, and integrate smart functionalities to boost productivity.
Home-page: https://github.com/liaoyusaki/efficienpy
License: BSD-3-Clause
Author: Yu LE VERN
Author-email: liaoyuviyy@gmail.com
Maintainer: Yu LE VERN
Maintainer-email: liaoyuviyy@gmail.com
Requires-Python: >=3.12,<4.0
Classifier: License :: OSI Approved :: BSD License
Classifier: Programming Language :: Python :: 3
Classifier: Programming Language :: Python :: 3.12
Project-URL: Documentation, https://github.com/liaoyusaki/efficienpy
Project-URL: Repository, https://github.com/liaoyusaki/efficienpy
